[
    {
        "name": "Aatrox",
        "alias": "aatrox",
        "gender": "male",
        "resource": "Manaless",
        "range_type": ["melee"],
        "release": 2013,
        "region": "runeterra,shurima",
        "species": ["Darkin"],
        "lane": "top"
    },
    {
        "name": "Ahri",
        "alias": "ahri",
        "gender": "female",
        "resource": "Mana",
        "range_type": ["ranged"],
        "release": 2011,
        "region": "ionia",
        "species": ["Vastayan"],
        "lane": "middle"
    },
    {
        "name": "Akali",
        "alias": "akali",
        "gender": "female",
        "resource": "Energy",
        "range_type": ["melee"],
        "release": 2010,
        "region": "ionia",
        "species": ["Human"],
        "lane": "top,middle"
    },
    {
        "name": "Akshan",
        "alias": "akshan",
        "gender": "male",
        "resource": "Mana",
        "range_type": ["ranged"],
        "release": 2021,
        "region": "shurima",
        "species": ["Human"],
        "lane": "middle"
    },
    {
        "name": "Alistar",
        "alias": "alistar",
        "gender": "male",
        "resource": "Mana",
        "range_type": ["melee"],
        "release": 2009,
        "region": "runeterra",
        "species": ["Minotaur"],
        "lane": "support"
    },
    {
        "name": "Ambessa",
        "alias": "ambessa",
        "gender": "female",
        "resource": "Energy",
        "range_type": ["melee"],
        "release": 2025,
        "region": "noxus,piltover",
        "species": ["Human"],
        "lane": "top,jungle"
    },
    {
        "name": "Amumu",
        "alias": "amumu",
        "gender": "male",
        "resource": "Mana",
        "range_type": ["melee"],
        "release": 2009,
        "region": "shurima",
        "species": ["Undead", "Yordle"],
        "lane": "jungle"
    },
    {
        "name": "Anivia",
        "alias": "anivia",
        "gender": "female",
        "resource": "Mana",
        "range_type": ["ranged"],
        "release": 2009,
        "region": "freljord",
        "species": ["God", "Spirit"],
        "lane": "middle"
    },
    {
        "name": "Annie",
        "alias": "annie",
        "gender": "female",
        "resource": "Mana",
        "range_type": ["ranged"],
        "release": 2009,
        "region": "noxus,runeterra",
        "species": ["Human", "Magicborn"],
        "lane": "middle"
    },
    {
        "name": "Aphelios",
        "alias": "aphelios",
        "gender": "male",
        "resource": "Mana",
        "range_type": ["ranged"],
        "release": 2019,
        "region": "targon",
        "species": ["Human", "Spiritualist"],
        "lane": "bottom"
    },
    {
        "name": "Ashe",
        "alias": "ashe",
        "gender": "female",
        "resource": "Mana",
        "range_type": ["ranged"],
        "release": 2009,
        "region": "freljord",
        "species": ["Human", "Iceborn"],
        "lane": "bottom,support"
    },
    {
        "name": "Aurelion Sol",
        "alias": "aurelionsol",
        "gender": "male",
        "resource": "Mana",
        "range_type": ["ranged"],
        "release": 2016,
        "region": "runeterra,targon",
        "species": ["Celestial", "Dragon"],
        "lane": "middle"
    },
    {
        "name": "Aurora",
        "alias": "aurora",
        "gender": "female",
        "resource": "Mana",
        "range_type": ["ranged"],
        "release": 2024,
        "region": "freljord",
        "species": ["Vastayan"],
        "lane": "top,middle"
    },
    {
        "name": "Azir",
        "alias": "azir",
        "gender": "male",
        "resource": "Mana",
        "range_type": ["ranged"],
        "release": 2014,
        "region": "shurima",
        "species": ["God-Warrior"],
        "lane": "middle"
    },
    {
        "name": "Bard",
        "alias": "bard",
        "gender": "male",
        "resource": "Mana",
        "range_type": ["ranged"],
        "release": 2015,
        "region": "runeterra",
        "species": ["Celestial"],
        "lane": "support"
    },
    {
        "name": "Bel'Veth",
        "alias": "belveth",
        "gender": "female",
        "resource": "Manaless",
        "range_type": ["melee"],
        "release": 2022,
        "region": "void",
        "species": ["Void-being"],
        "lane": "jungle"
    },
    {
        "name": "Blitzcrank",
        "alias": "blitzcrank",
        "gender": "Other",
        "resource": "Mana",
        "range_type": ["melee"],
        "release": 2009,
        "region": "zaun",
        "species": ["Golem"],
        "lane": "support"
    },
    {
        "name": "Brand",
        "alias": "brand",
        "gender": "male",
        "resource": "Mana",
        "range_type": ["ranged"],
        "release": 2011,
        "region": "freljord,runeterra",
        "species": ["Human", "Magically Altered"],
        "lane": "jungle,support"
    },
    {
        "name": "Braum",
        "alias": "braum",
        "gender": "male",
        "resource": "Mana",
        "range_type": ["melee"],
        "release": 2014,
        "region": "freljord",
        "species": ["Human", "Iceborn"],
        "lane": "support"
    },
    {
        "name": "Briar",
        "alias": "briar",
        "gender": "female",
        "resource": "Health costs",
        "range_type": ["melee"],
        "release": 2023,
        "region": "noxus",
        "species": ["Golem"],
        "lane": "jungle"
    },
    {
        "name": "Caitlyn",
        "alias": "caitlyn",
        "gender": "female",
        "resource": "Mana",
        "range_type": ["ranged"],
        "release": 2011,
        "region": "piltover",
        "species": ["Human"],
        "lane": "bottom"
    },
    {
        "name": "Camille",
        "alias": "camille",
        "gender": "female",
        "resource": "Mana",
        "range_type": ["melee"],
        "release": 2016,
        "region": "piltover",
        "species": ["Cyborg", "Human"],
        "lane": "top"
    },
    {
        "name": "Cassiopeia",
        "alias": "cassiopeia",
        "gender": "female",
        "resource": "Mana",
        "range_type": ["ranged"],
        "release": 2010,
        "region": "noxus,shurima",
        "species": ["Human", "Magically Altered"],
        "lane": "middle"
    },
    {
        "name": "Cho'Gath",
        "alias": "chogath",
        "gender": "male",
        "resource": "Mana",
        "range_type": ["melee"],
        "release": 2009,
        "region": "void",
        "species": ["Void-being"],
        "lane": "top"
    },
    {
        "name": "Corki",
        "alias": "corki",
        "gender": "male",
        "resource": "Mana",
        "range_type": ["ranged"],
        "release": 2009,
        "region": "bandle-city,piltover",
        "species": ["Yordle"],
        "lane": "middle,bottom"
    },
    {
        "name": "Darius",
        "alias": "darius",
        "gender": "male",
        "resource": "Mana",
        "range_type": ["melee"],
        "release": 2012,
        "region": "noxus",
        "species": ["Human"],
        "lane": "top"
    },
    {
        "name": "Diana",
        "alias": "diana",
        "gender": "female",
        "resource": "Mana",
        "range_type": ["melee"],
        "release": 2012,
        "region": "targon",
        "species": ["Human", "Aspect"],
        "lane": "jungle,middle"
    },
    {
        "name": "Draven",
        "alias": "draven",
        "gender": "male",
        "resource": "Mana",
        "range_type": ["ranged"],
        "release": 2012,
        "region": "noxus",
        "species": ["Human"],
        "lane": "bottom"
    },
    {
        "name": "Dr. Mundo",
        "alias": "drmundo",
        "gender": "male",
        "resource": "Health costs",
        "range_type": ["melee"],
        "release": 2009,
        "region": "zaun",
        "species": ["Chemically Altered", "Human"],
        "lane": "top"
    },
    {
        "name": "Ekko",
        "alias": "ekko",
        "gender": "male",
        "resource": "Mana",
        "range_type": ["melee"],
        "release": 2015,
        "region": "zaun",
        "species": ["Human"],
        "lane": "jungle,middle"
    },
    {
        "name": "Elise",
        "alias": "elise",
        "gender": "female",
        "resource": "Mana",
        "range_type": [
            "melee",
            "ranged"
        ],
        "release": 2012,
        "region": "noxus,shadow-isles",
        "species": ["Human", "Magically Altered"],
        "lane": "jungle"
    },
    {
        "name": "Evelynn",
        "alias": "evelynn",
        "gender": "female",
        "resource": "Mana",
        "range_type": ["melee"],
        "release": 2009,
        "region": "runeterra",
        "species": ["Demon", "Spirit"],
        "lane": "jungle"
    },
    {
        "name": "Ezreal",
        "alias": "ezreal",
        "gender": "male",
        "resource": "Mana",
        "range_type": ["ranged"],
        "release": 2010,
        "region": "piltover",
        "species": ["Human", "Magicborn"],
        "lane": "bottom"
    },
    {
        "name": "Fiddlesticks",
        "alias": "fiddlesticks",
        "gender": "Other",
        "resource": "Mana",
        "range_type": ["melee"],
        "release": 2009,
        "region": "runeterra",
        "species": ["Demon", "Spirit"],
        "lane": "jungle"
    },
    {
        "name": "Fiora",
        "alias": "fiora",
        "gender": "female",
        "resource": "Mana",
        "range_type": ["melee"],
        "release": 2012,
        "region": "demacia",
        "species": ["Human"],
        "lane": "top"
    },
    {
        "name": "Fizz",
        "alias": "fizz",
        "gender": "male",
        "resource": "Mana",
        "range_type": ["melee"],
        "release": 2011,
        "region": "bilgewater",
        "species": ["Yordle"],
        "lane": "middle"
    },
    {
        "name": "Galio",
        "alias": "galio",
        "gender": "male",
        "resource": "Mana",
        "range_type": ["melee"],
        "release": 2010,
        "region": "demacia",
        "species": ["Golem"],
        "lane": "middle"
    },
    {
        "name": "Gangplank",
        "alias": "gangplank",
        "gender": "male",
        "resource": "Mana",
        "range_type": ["melee"],
        "release": 2009,
        "region": "bilgewater",
        "species": ["Human"],
        "lane": "top"
    },
    {
        "name": "Garen",
        "alias": "garen",
        "gender": "male",
        "resource": "Manaless",
        "range_type": ["melee"],
        "release": 2010,
        "region": "demacia",
        "species": ["Human"],
        "lane": "top"
    },
    {
        "name": "Gnar",
        "alias": "gnar",
        "gender": "male",
        "resource": "Rage",
        "range_type": [
            "melee",
            "ranged"
        ],
        "release": 2014,
        "region": "freljord",
        "species": ["Yordle"],
        "lane": "top"
    },
    {
        "name": "Gragas",
        "alias": "gragas",
        "gender": "male",
        "resource": "Mana",
        "range_type": ["melee"],
        "release": 2010,
        "region": "freljord",
        "species": ["Human", "Iceborn"],
        "lane": "jungle,top"
    },
    {
        "name": "Graves",
        "alias": "graves",
        "gender": "male",
        "resource": "Mana",
        "range_type": ["melee"],
        "release": 2011,
        "region": "bilgewater",
        "species": ["Human"],
        "lane": "jungle"
    },
    {
        "name": "Gwen",
        "alias": "gwen",
        "gender": "female",
        "resource": "Mana",
        "range_type": ["melee"],
        "release": 2021,
        "region": "shadow-isles,camavor",
        "species": ["Human", "Magically Altered"],
        "lane": "top,jungle"
    },
    {
        "name": "Hecarim",
        "alias": "hecarim",
        "gender": "male",
        "resource": "Mana",
        "range_type": ["melee"],
        "release": 2012,
        "region": "shadow-isles,camavor",
        "species": ["Undead"],
        "lane": "jungle"
    },
    {
        "name": "Heimerdinger",
        "alias": "heimerdinger",
        "gender": "male",
        "resource": "Mana",
        "range_type": ["ranged"],
        "release": 2009,
        "region": "piltover",
        "species": ["Yordle"],
        "lane": "top,middle"
    },
    {
        "name": "Hwei",
        "alias": "hwei",
        "gender": "male",
        "resource": "Mana",
        "range_type": ["ranged"],
        "release": 2023,
        "region": "ionia",
        "species": ["Human", "Magicborn"],
        "lane": "middle"
    },
    {
        "name": "Illaoi",
        "alias": "illaoi",
        "gender": "female",
        "resource": "Mana",
        "range_type": ["melee"],
        "release": 2015,
        "region": "bilgewater",
        "species": ["Human", "Spiritualist"],
        "lane": "top"
    },
    {
        "name": "Irelia",
        "alias": "irelia",
        "gender": "female",
        "resource": "Mana",
        "range_type": ["melee"],
        "release": 2010,
        "region": "ionia",
        "species": ["Human", "Spiritualist"],
        "lane": "top,middle"
    },
    {
        "name": "Ivern",
        "alias": "ivern",
        "gender": "male",
        "resource": "Mana",
        "range_type": ["ranged"],
        "release": 2016,
        "region": "ionia,freljord",
        "species": ["Human", "Magically Altered"],
        "lane": "jungle"
    },
    {
        "name": "Janna",
        "alias": "janna",
        "gender": "female",
        "resource": "Mana",
        "range_type": ["ranged"],
        "release": 2009,
        "region": "zaun,shurima",
        "species": ["God", "Spirit"],
        "lane": "support"
    },
    {
        "name": "Jarvan IV",
        "alias": "jarvan iv",
        "gender": "male",
        "resource": "Mana",
        "range_type": ["melee"],
        "release": 2011,
        "region": "demacia",
        "species": ["Human"],
        "lane": "jungle"
    },
    {
        "name": "Jax",
        "alias": "jax",
        "gender": "male",
        "resource": "Mana",
        "range_type": ["melee"],
        "release": 2009,
        "region": "runeterra,icathia,shurima",
        "species": ["Unknown"],
        "lane": "top,jungle"
    },
    {
        "name": "Jayce",
        "alias": "jayce",
        "gender": "male",
        "resource": "Mana",
        "range_type": [
            "melee",
            "ranged"
        ],
        "release": 2012,
        "region": "piltover",
        "species": ["Human"],
        "lane": "top,middle"
    },
    {
        "name": "Jhin",
        "alias": "jhin",
        "gender": "male",
        "resource": "Mana",
        "range_type": ["ranged"],
        "release": 2016,
        "region": "ionia",
        "species": ["Human", "Spiritualist"],
        "lane": "bottom"
    },
    {
        "name": "Jinx",
        "alias": "jinx",
        "gender": "female",
        "resource": "Mana",
        "range_type": ["ranged"],
        "release": 2013,
        "region": "zaun",
        "species": ["Human", "Chemically Altered"],
        "lane": "bottom"
    },
    {
        "name": "K'Sante",
        "alias": "ksante",
        "gender": "male",
        "resource": "Mana",
        "range_type": ["melee"],
        "release": 2022,
        "region": "shurima",
        "species": ["Human"],
        "lane": "top"
    },
    {
        "name": "Kai'Sa",
        "alias": "kaisa",
        "gender": "female",
        "resource": "Mana",
        "range_type": ["ranged"],
        "release": 2018,
        "region": "void,shurima",
        "species": ["Human", "Void-being"],
        "lane": "bottom"
    },
    {
        "name": "Kalista",
        "alias": "kalista",
        "gender": "female",
        "resource": "Mana",
        "range_type": ["ranged"],
        "release": 2014,
        "region": "shadow-isles,camavor",
        "species": ["Undead"],
        "lane": "bottom"
    },
    {
        "name": "Karma",
        "alias": "karma",
        "gender": "female",
        "resource": "Mana",
        "range_type": ["ranged"],
        "release": 2011,
        "region": "ionia",
        "species": ["Human", "Spiritualist"],
        "lane": "support"
    },
    {
        "name": "Karthus",
        "alias": "karthus",
        "gender": "male",
        "resource": "Mana",
        "range_type": ["ranged"],
        "release": 2009,
        "region": "shadow-isles,noxus",
        "species": ["Undead"],
        "lane": "jungle"
    },
    {
        "name": "Kassadin",
        "alias": "kassadin",
        "gender": "male",
        "resource": "Mana",
        "range_type": ["melee"],
        "release": 2009,
        "region": "void,shurima",
        "species": ["Human", "Void-being"],
        "lane": "middle"
    },
    {
        "name": "Katarina",
        "alias": "katarina",
        "gender": "female",
        "resource": "Manaless",
        "range_type": ["melee"],
        "release": 2009,
        "region": "noxus",
        "species": ["Human"],
        "lane": "middle"
    },
    {
        "name": "Kayle",
        "alias": "kayle",
        "gender": "female",
        "resource": "Mana",
        "range_type": [
            "melee",
            "ranged"
        ],
        "release": 2009,
        "region": "demacia,targon",
        "species": ["Aspect", "Human", "Magically Altered"],
        "lane": "top"
    },
    {
        "name": "Kayn",
        "alias": "kayn",
        "gender": "male",
        "resource": "Mana",
        "range_type": ["melee"],
        "release": 2017,
        "region": "ionia,noxus,runeterra,shurima",
        "species": ["Darkin", "Human", "Magically Altered"],
        "lane": "jungle"
    },
    {
        "name": "Kennen",
        "alias": "kennen",
        "gender": "male",
        "resource": "Energy",
        "range_type": ["ranged"],
        "release": 2010,
        "region": "ionia",
        "species": ["Yordle"],
        "lane": "top"
    },
    {
        "name": "Kha'Zix",
        "alias": "kha'zix",
        "gender": "male",
        "resource": "Mana",
        "range_type": ["melee"],
        "release": 2012,
        "region": "void",
        "species": ["Void-being"],
        "lane": "jungle"
    },
    {
        "name": "Kindred",
        "alias": "kindred",
        "gender": "Other",
        "resource": "Mana",
        "range_type": ["ranged"],
        "release": 2015,
        "region": "runeterra",
        "species": ["God", "Spirit"],
        "lane": "jungle"
    },
    {
        "name": "Kled",
        "alias": "kled",
        "gender": "male",
        "resource": "Courage",
        "range_type": ["melee"],
        "release": 2016,
        "region": "noxus",
        "species": ["Yordle"],
        "lane": "top"
    },
    {
        "name": "Kog'Maw",
        "alias": "kog'maw",
        "gender": "male",
        "resource": "Mana",
        "range_type": ["ranged"],
        "release": 2010,
        "region": "void",
        "species": ["Void-being"],
        "lane": "bottom"
    },   
    {
        "name": "LeBlanc",
        "alias": "leblanc",
        "gender": "female",
        "resource": "Mana",
        "range_type": ["ranged"],
        "release": 2010,
        "region": "noxus",
        "species": ["Human", "Magically Altered"],
        "lane": "middle"
    },
    {
        "name": "Lee Sin",
        "alias": "lee sin",
        "gender": "male",
        "resource": "Energy",
        "range_type": ["melee"],
        "release": 2011,
        "region": "ionia",
        "species": ["Human", "Spiritualist"],
        "lane": "jungle"
    },
    {
        "name": "Leona",
        "alias": "leona",
        "gender": "female",
        "resource": "Mana",
        "range_type": ["melee"],
        "release": 2011,
        "region": "targon",
        "species": ["Aspect", "Human"],
        "lane": "support"
    },
    {
        "name": "Lillia",
        "alias": "lillia",
        "gender": "female",
        "resource": "Mana",
        "range_type": ["melee"],
        "release": 2020,
        "region": "ionia",
        "species": ["Spirit"],
        "lane": "jungle"
    },
    {
        "name": "Lissandra",
        "alias": "lissandra",
        "gender": "female",
        "resource": "Mana",
        "range_type": ["ranged"],
        "release": 2013,
        "region": "freljord",
        "species": ["Human", "Iceborn"],
        "lane": "middle"
    },
    {
        "name": "Lucian",
        "alias": "lucian",
        "gender": "male",
        "resource": "Mana",
        "range_type": ["ranged"],
        "release": 2013,
        "region": "demacia,shadow-isles",
        "species": ["Human"],
        "lane": "bottom"
    },
    {
        "name": "Lulu",
        "alias": "lulu",
        "gender": "female",
        "resource": "Mana",
        "range_type": ["ranged"],
        "release": 2012,
        "region": "bandle-city",
        "species": ["Yordle"],
        "lane": "support"
    },
    {
        "name": "Lux",
        "alias": "lux",
        "gender": "female",
        "resource": "Mana",
        "range_type": ["ranged"],
        "release": 2010,
        "region": "demacia",
        "species": ["Human", "Magicborn"],
        "lane": "middle,support"
    },
    {
        "name": "Malphite",
        "alias": "malphite",
        "gender": "male",
        "resource": "Mana",
        "range_type": ["melee"],
        "release": 2009,
        "region": "ixtal,shurima",
        "species": ["Golem"],
        "lane": "top"
    },
    {
        "name": "Malzahar",
        "alias": "malzahar",
        "gender": "male",
        "resource": "Mana",
        "range_type": ["ranged"],
        "release": 2010,
        "region": "void,shurima",
        "species": ["Human", "Void-being"],
        "lane": "middle"
    },
    {
        "name": "Maokai",
        "alias": "maokai",
        "gender": "male",
        "resource": "Mana",
        "range_type": ["melee"],
        "release": 2011,
        "region": "shadow-isles",
        "species": ["Spirit"],
        "lane": "support,top"
    },
    {
        "name": "Master Yi",
        "alias": "master yi",
        "gender": "male",
        "resource": "Mana",
        "range_type": ["melee"],
        "release": 2009,
        "region": "ionia",
        "species": ["Human", "Spiritualist"],
        "lane": "jungle"
    },
    {
        "name": "Mel",
        "alias": "mel",
        "gender": "female",
        "resource": "Mana",
        "range_type": ["ranged"],
        "release": 2025,
        "region": "noxus,piltover",
        "species": ["Human", "Magically Altered"],
        "lane": "middle,support"
    },
    {
        "name": "Milio",
        "alias": "milio",
        "gender": "male",
        "resource": "Mana",
        "range_type": ["ranged"],
        "release": 2023,
        "region": "ixtal",
        "species": ["Human", "Magicborn"],
        "lane": "support"
    },
    {
        "name": "Miss Fortune",
        "alias": "missfortune",
        "gender": "female",
        "resource": "Mana",
        "range_type": ["ranged"],
        "release": 2010,
        "region": "bilgewater",
        "species": ["Human"],
        "lane": "bottom"
    },
    {
        "name": "Wukong",
        "alias": "wukong",
        "gender": "male",
        "resource": "Mana",
        "range_type": ["melee"],
        "release": 2011,
        "region": "ionia",
        "species": ["Vastayan"],
        "lane": "jungle,top"
    },
    {
        "name": "Mordekaiser",
        "alias": "mordekaiser",
        "gender": "male",
        "resource": "Shield",
        "range_type": ["melee"],
        "release": 2010,
        "region": "noxus,shadow-isles",
        "species": ["Revenant"],
        "lane": "top"
    },
    {
        "name": "Morgana",
        "alias": "morgana",
        "gender": "female",
        "resource": "Mana",
        "range_type": ["ranged"],
        "release": 2009,
        "region": "demacia,targon",
        "species": ["Aspect", "Human", "Magically Altered"],
        "lane": "support"
    },
    {
        "name": "Naafiri",
        "alias": "naafiri",
        "gender": "female",
        "resource": "Mana",
        "range_type": ["melee"],
        "release": 2023,
        "region": "shurima",
        "species": ["Darkin", "Dog"],
        "lane": "middle"
    },
    {
        "name": "Nami",
        "alias": "nami",
        "gender": "female",
        "resource": "Mana",
        "range_type": ["ranged"],
        "release": 2012,
        "region": "runeterra,bilgewater",
        "species": ["Vastayan"],
        "lane": "support"
    },
    {
        "name": "Nasus",
        "alias": "nasus",
        "gender": "male",
        "resource": "Mana",
        "range_type": ["melee"],
        "release": 2009,
        "region": "shurima",
        "species": ["God-Warrior"],
        "lane": "top"
    },
    {
        "name": "Nautilus",
        "alias": "nautilus",
        "gender": "male",
        "resource": "Mana",
        "range_type": ["melee"],
        "release": 2012,
        "region": "bilgewater",
        "species": ["Revenant"],
        "lane": "support"
    },
    {
        "name": "Neeko",
        "alias": "neeko",
        "gender": "female",
        "resource": "Mana",
        "range_type": ["ranged"],
        "release": 2018,
        "region": "ixtal",
        "species": ["Vastayan"],
        "lane": "middle,support"
    },
    {
        "name": "Nidalee",
        "alias": "nidalee",
        "gender": "female",
        "resource": "Mana",
        "range_type": [
            "melee",
            "ranged"
        ],
        "release": 2009,
        "region": "ixtal",
        "species": ["Human", "Spiritualist"],
        "lane": "jungle"
    },
    {
        "name": "Nilah",
        "alias": "nilah",
        "gender": "female",
        "resource": "Mana",
        "range_type": ["melee"],
        "release": 2022,
        "region": "runeterra",
        "species": ["Human", "Magically Altered"],
        "lane": "bottom"
    },
    {
        "name": "Nocturne",
        "alias": "nocturne",
        "gender": "Other",
        "resource": "Mana",
        "range_type": ["melee"],
        "release": 2011,
        "region": "runeterra",
        "species": ["Demon", "Spirit"],
        "lane": "jungle"
    },
    {
        "name": "Nunu & Willump",
        "alias": "nunu & willump",
        "gender": "male",
        "resource": "Mana",
        "range_type": ["melee"],
        "release": 2009,
        "region": "freljord",
        "species": ["Human", "Yeti"],
        "lane": "jungle"
    },
    {
        "name": "Olaf",
        "alias": "olaf",
        "gender": "male",
        "resource": "Mana",
        "range_type": ["melee"],
        "release": 2010,
        "region": "freljord",
        "species": ["Human", "Iceborn"],
        "lane": "top"
    },
    {
        "name": "Orianna",
        "alias": "orianna",
        "gender": "female",
        "resource": "Mana",
        "range_type": ["ranged"],
        "release": 2011,
        "region": "piltover",
        "species": ["Golem"],
        "lane": "middle"
    },
    {
        "name": "Ornn",
        "alias": "ornn",
        "gender": "male",
        "resource": "Mana",
        "range_type": ["melee"],
        "release": 2017,
        "region": "freljord",
        "species": ["God", "Spirit"],
        "lane": "top"
    },
    {
        "name": "Pantheon",
        "alias": "pantheon",
        "gender": "male",
        "resource": "Mana",
        "range_type": ["melee"],
        "release": 2010,
        "region": "targon",
        "species": ["Human", "Aspect"],
        "lane": "top,support"
    },
    {
        "name": "Poppy",
        "alias": "poppy",
        "gender": "female",
        "resource": "Mana",
        "range_type": ["melee"],
        "release": 2010,
        "region": "demacia",
        "species": ["Yordle"],
        "lane": "top,support"
    },
    {
        "name": "Pyke",
        "alias": "pyke",
        "gender": "male",
        "resource": "Mana",
        "range_type": ["melee"],
        "release": 2018,
        "region": "bilgewater",
        "species": ["Revenant"],
        "lane": "support"
    },
    {
        "name": "Qiyana",
        "alias": "qiyana",
        "gender": "female",
        "resource": "Mana",
        "range_type": ["melee"],
        "release": 2019,
        "region": "ixtal",
        "species": ["Human", "Magicborn"],
        "lane": "middle"
    },
    {
        "name": "Quinn",
        "alias": "quinn",
        "gender": "female",
        "resource": "Mana",
        "range_type": ["ranged"],
        "release": 2013,
        "region": "demacia",
        "species": ["Human"],
        "lane": "top"
    },
    {
        "name": "Rakan",
        "alias": "rakan",
        "gender": "male",
        "resource": "Mana",
        "range_type": ["melee"],
        "release": 2017,
        "region": "ionia",
        "species": ["Vastayan"],
        "lane": "support"
    },
    {
        "name": "Rammus",
        "alias": "rammus",
        "gender": "male",
        "resource": "Mana",
        "range_type": ["melee"],
        "release": 2009,
        "region": "shurima",
        "species": ["Unknown"],
        "lane": "jungle"
    },
    {
        "name": "Rek'Sai",
        "alias": "reksai",
        "gender": "female",
        "resource": "Rage",
        "range_type": ["melee"],
        "release": 2014,
        "region": "void,shurima",
        "species": ["Void-being"],
        "lane": "jungle"
    },
    {
        "name": "Rell",
        "alias": "rell",
        "gender": "female",
        "resource": "Mana",
        "range_type": ["melee"],
        "release": 2020,
        "region": "noxus",
        "species": ["Human", "Magically Altered", "Magicborn"],
        "lane": "support"
    },
    {
        "name": "Renata Glasc",
        "alias": "renata glasc",
        "gender": "female",
        "resource": "Mana",
        "range_type": ["ranged"],
        "release": 2022,
        "region": "zaun",
        "species": ["Chemically Altered", "Human"],
        "lane": "support"
    },
    {
        "name": "Renekton",
        "alias": "renekton",
        "gender": "male",
        "resource": "Fury",
        "range_type": ["melee"],
        "release": 2011,
        "region": "shurima",
        "species": ["God-Warrior"],
        "lane": "top"
    },
    {
        "name": "Rengar",
        "alias": "rengar",
        "gender": "male",
        "resource": "Ferocity",
        "range_type": ["melee"],
        "release": 2012,
        "region": "ixtal,shurima",
        "species": ["Vastayan"],
        "lane": "jungle"
    },
    {
        "name": "Riven",
        "alias": "riven",
        "gender": "female",
        "resource": "Manaless",
        "range_type": ["melee"],
        "release": 2011,
        "region": "noxus,ionia",
        "species": ["Human"],
        "lane": "top"
    },
    {
        "name": "Rumble",
        "alias": "rumble",
        "gender": "male",
        "resource": "Heat",
        "range_type": ["melee"],
        "release": 2011,
        "region": "bandle-city",
        "species": ["Yordle"],
        "lane": "top"
    },
    {
        "name": "Ryze",
        "alias": "ryze",
        "gender": "male",
        "resource": "Mana",
        "range_type": ["ranged"],
        "release": 2009,
        "region": "runeterra",
        "species": ["Human", "Magically Altered"],
        "lane": "middle,top"
    },
    {
        "name": "Samira",
        "alias": "samira",
        "gender": "female",
        "resource": "Mana",
        "range_type": ["ranged"],
        "release": 2020,
        "region": "noxus,shurima",
        "species": ["Human"],
        "lane": "bottom"
    },
    {
        "name": "Sejuani",
        "alias": "sejuani",
        "gender": "female",
        "resource": "Mana",
        "range_type": ["melee"],
        "release": 2012,
        "region": "freljord",
        "species": ["Human", "Iceborn"],
        "lane": "jungle"
    },
    {
        "name": "Senna",
        "alias": "senna",
        "gender": "female",
        "resource": "Mana",
        "range_type": ["ranged"],
        "release": 2019,
        "region": "shadow-isles",
        "species": ["Human", "Undead"],
        "lane": "support"
    },
    {
        "name": "Seraphine",
        "alias": "seraphine",
        "gender": "female",
        "resource": "Mana",
        "range_type": ["ranged"],
        "release": 2020,
        "region": "piltover,zaun",
        "species": ["Human", "Magicborn"],
        "lane": "support"
    },
    {
        "name": "Sett",
        "alias": "sett",
        "gender": "male",
        "resource": "Grit",
        "range_type": ["melee"],
        "release": 2020,
        "region": "ionia",
        "species": ["Human", "Vastayan"],
        "lane": "top"
    },
    {
        "name": "Shaco",
        "alias": "shaco",
        "gender": "male",
        "resource": "Mana",
        "range_type": ["melee"],
        "release": 2009,
        "region": "runeterra",
        "species": ["Spirit"],
        "lane": "jungle"
    },
    {
        "name": "Shen",
        "alias": "shen",
        "gender": "male",
        "resource": "Energy",
        "range_type": ["melee"],
        "release": 2010,
        "region": "ionia",
        "species": ["Human", "Spiritualist"],
        "lane": "top,support"
    },
    {
        "name": "Shyvana",
        "alias": "shyvana",
        "gender": "female",
        "resource": "Fury",
        "range_type": ["melee"],
        "release": 2011,
        "region": "demacia",
        "species": ["Dragon", "Magically Altered"],
        "lane": "jungle"
    },
    {
        "name": "Singed",
        "alias": "singed",
        "gender": "male",
        "resource": "Mana",
        "range_type": ["melee"],
        "release": 2009,
        "region": "zaun,piltover",
        "species": ["Chemically Altered", "Human"],
        "lane": "top"
    },
    {
        "name": "Sion",
        "alias": "sion",
        "gender": "male",
        "resource": "Mana",
        "range_type": ["melee"],
        "release": 2009,
        "region": "noxus",
        "species": ["Revenant"],
        "lane": "top"
    },
    {
        "name": "Sivir",
        "alias": "sivir",
        "gender": "female",
        "resource": "Mana",
        "range_type": ["ranged"],
        "release": 2009,
        "region": "shurima",
        "species": ["Human"],
        "lane": "bottom"
    },
    {
        "name": "Skarner",
        "alias": "skarner",
        "gender": "male",
        "resource": "Mana",
        "range_type": ["melee"],
        "release": 2011,
        "region": "ixtal",
        "species": ["Brackern"],
        "lane": "jungle"
    },
    {
        "name": "Smolder",
        "alias": "smolder",
        "gender": "male",
        "resource": "Mana",
        "range_type": ["ranged"],
        "release": 2024,
        "region": "camavor,noxus",
        "species": ["Dragon"],
        "lane": "bottom,middle"
    },
    {
        "name": "Sona",
        "alias": "sona",
        "gender": "female",
        "resource": "Mana",
        "range_type": ["ranged"],
        "release": 2010,
        "region": "demacia,ionia",
        "species": ["Human", "Magicborn"],
        "lane": "support"
    },
    {
        "name": "Soraka",
        "alias": "soraka",
        "gender": "female",
        "resource": "Mana",
        "range_type": ["ranged"],
        "release": 2009,
        "region": "targon,ionia",
        "species": ["Celestial"],
        "lane": "support"
    },
    {
        "name": "Swain",
        "alias": "swain",
        "gender": "male",
        "resource": "Mana",
        "range_type": ["ranged"],
        "release": 2010,
        "region": "noxus",
        "species": ["Human", "Magically Altered"],
        "lane": "support"
    },
    {
        "name": "Sylas",
        "alias": "sylas",
        "gender": "male",
        "resource": "Mana",
        "range_type": ["melee"],
        "release": 2019,
        "region": "demacia,freljord",
        "species": ["Human", "Magicborn"],
        "lane": "middle"
    },
    {
        "name": "Syndra",
        "alias": "syndra",
        "gender": "female",
        "resource": "Mana",
        "range_type": ["ranged"],
        "release": 2012,
        "region": "ionia",
        "species": ["Human", "Magicborn"],
        "lane": "middle"
    },
    {
        "name": "Tahm Kench",
        "alias": "tahm kench",
        "gender": "male",
        "resource": "Mana",
        "range_type": ["melee"],
        "release": 2015,
        "region": "bilgewater,runeterra",
        "species": ["Demon", "Spirit"],
        "lane": "top,support"
    },
    {
        "name": "Taliyah",
        "alias": "taliyah",
        "gender": "female",
        "resource": "Mana",
        "range_type": ["ranged"],
        "release": 2016,
        "region": "shurima",
        "species": ["Human", "Magicborn"],
        "lane": "jungle,middle"
    },
    {
        "name": "Talon",
        "alias": "talon",
        "gender": "male",
        "resource": "Mana",
        "range_type": ["melee"],
        "release": 2011,
        "region": "noxus",
        "species": ["Human"],
        "lane": "jundle,middle"
    },
    {
        "name": "Taric",
        "alias": "taric",
        "gender": "male",
        "resource": "Mana",
        "range_type": ["melee"],
        "release": 2009,
        "region": "targon",
        "species": ["Aspect", "Human"],
        "lane": "support"
    },
    {
        "name": "Teemo",
        "alias": "teemo",
        "gender": "male",
        "resource": "Mana",
        "range_type": ["ranged"],
        "release": 2009,
        "region": "bandle-city",
        "species": ["Yordle"],
        "lane": "top,jungle"
    },
    {
        "name": "Thresh",
        "alias": "thresh",
        "gender": "male",
        "resource": "Mana",
        "range_type": ["ranged"],
        "release": 2013,
        "region": "shadow-isles",
        "species": ["Undead"],
        "lane": "support"
    },
    {
        "name": "Tristana",
        "alias": "tristana",
        "gender": "female",
        "resource": "Mana",
        "range_type": ["ranged"],
        "release": 2009,
        "region": "bandle-city",
        "species": ["Yordle"],
        "lane": "bottom"
    },
    {
        "name": "Trundle",
        "alias": "trundle",
        "gender": "male",
        "resource": "Mana",
        "range_type": ["melee"],
        "release": 2010,
        "region": "freljord",
        "species": ["Iceborn", "Troll"],
        "lane": "top,jungle"
    },
    {
        "name": "Tryndamere",
        "alias": "tryndamere",
        "gender": "male",
        "resource": "Fury",
        "range_type": ["melee"],
        "release": 2009,
        "region": "freljord",
        "species": ["Human", "Magically Altered"],
        "lane": "top"
    },
    {
        "name": "Twisted Fate",
        "alias": "twisted fate",
        "gender": "male",
        "resource": "Mana",
        "range_type": ["ranged"],
        "release": 2009,
        "region": "bilgewater",
        "species": ["Human", "Magicborn"],
        "lane": "middle"
    },
    {
        "name": "Twitch",
        "alias": "twitch",
        "gender": "male",
        "resource": "Mana",
        "range_type": ["ranged"],
        "release": 2009,
        "region": "zaun",
        "species": ["Chemically Altered", "Rat"],
        "lane": "bottom"
    },
    {
        "name": "Udyr",
        "alias": "udyr",
        "gender": "male",
        "resource": "Mana",
        "range_type": ["melee"],
        "release": 2009,
        "region": "freljord",
        "lane": "top,jungle"
    },
    {
        "name": "Urgot",
        "alias": "urgot",
        "gender": "male",
        "resource": "Mana",
        "range_type": ["melee"],
        "release": 2010,
        "region": "zaun",
        "lane": "top"
    },
    {
        "name": "Varus",
        "alias": "varus",
        "gender": "male",
        "resource": "Mana",
        "range_type": ["ranged"],
        "release": 2012,
        "region": "ionia",
        "lane": "bottom"
    },
    {
        "name": "Vayne",
        "alias": "vayne",
        "gender": "female",
        "resource": "Mana",
        "range_type": ["ranged"],
        "release": 2011,
        "region": "demacia",
        "lane": "bottom"
    },
    {
        "name": "Veigar",
        "alias": "veigar",
        "gender": "male",
        "resource": "Mana",
        "range_type": ["ranged"],
        "release": 2009,
        "region": "bandle-city",
        "lane": "middle"
    },
    {
        "name": "Vel'Koz",
        "alias": "vel'koz",
        "gender": "male",
        "resource": "Mana",
        "range_type": ["ranged"],
        "release": 2014,
        "region": "void",
        "lane": "support"
    },
    {
        "name": "Vex",
        "alias": "vex",
        "gender": "female",
        "resource": "Mana",
        "range_type": ["ranged"],
        "release": 2021,
        "region": "shadow-isles",
        "lane": "middle"
    },
    {
        "name": "Vi",
        "alias": "vi",
        "gender": "female",
        "resource": "Mana",
        "range_type": ["melee"],
        "release": 2012,
        "region": "piltover",
        "lane": "jungle"
    },
    {
        "name": "Viego",
        "alias": "viego",
        "gender": "male",
        "resource": "None",
        "range_type": ["melee"],
        "release": 2021,
        "region": "shadow-isles",
        "lane": "jungle"
    },
    {
        "name": "Viktor",
        "alias": "viktor",
        "gender": "male",
        "resource": "Mana",
        "range_type": ["ranged"],
        "release": 2011,
        "region": "zaun",
        "lane": "middle"
    },
    {
        "name": "Vladimir",
        "alias": "vladimir",
        "gender": "male",
        "resource": "Crimson Rush",
        "range_type": ["melee"],
        "release": 2010,
        "region": "noxus",
        "lane": "middle"
    },
    {
        "name": "Volibear",
        "alias": "volibear",
        "gender": "male",
        "resource": "Mana",
        "range_type": ["melee"],
        "release": 2011,
        "region": "freljord",
        "lane": "top"
    },
    {
        "name": "Warwick",
        "alias": "warwick",
        "gender": "male",
        "resource": "Mana",
        "range_type": ["melee"],
        "release": 2009,
        "region": "zaun",
        "lane": "jungle"
    },
    {
        "name": "Xayah",
        "alias": "xayah",
        "gender": "female",
        "resource": "Mana",
        "range_type": ["ranged"],
        "release": 2017,
        "region": "ionia",
        "lane": "bottom"
    },
    {
        "name": "Xerath",
        "alias": "xerath",
        "gender": "male",
        "resource": "Mana",
        "range_type": ["ranged"],
        "release": 2011,
        "region": "shurima",
        "lane": "middle,support"
    },
    {
        "name": "Xin Zhao",
        "alias": "xin zhao",
        "gender": "male",
        "resource": "Mana",
        "range_type": ["melee"],
        "release": 2010,
        "region": "demacia",
        "lane": "jungle"
    },
    {
        "name": "Yasuo",
        "alias": "yasuo",
        "gender": "male",
        "resource": "Flow",
        "range_type": ["melee"],
        "release": 2013,
        "region": "ionia",
        "lane": "top,middle,bottom"
    },
    {
        "name": "Yone",
        "alias": "yone",
        "gender": "male",
        "resource": "Flow",
        "range_type": ["melee"],
        "release": 2020,
        "region": "ionia",
        "lane": "top,middle"
    },
    {
        "name": "Yorick",
        "alias": "yorick",
        "gender": "male",
        "resource": "Mana",
        "range_type": ["melee"],
        "release": 2011,
        "region": "shadow-isles",
        "lane": "top"
    },
    {
        "name": "Yuumi",
        "alias": "yuumi",
        "gender": "female",
        "resource": "Mana",
        "range_type": ["melee"],
        "release": 2019,
        "region": "bandle-city",
        "lane": "support"
    },
    {
        "name": "Zac",
        "alias": "zac",
        "gender": "male",
        "resource": "None",
        "range_type": ["melee"],
        "release": 2013,
        "region": "zaun",
        "lane": "jungle"
    },
    {
        "name": "Zed",
        "alias": "zed",
        "gender": "male",
        "resource": "Energy",
        "range_type": ["melee"],
        "release": 2012,
        "region": "ionia",
        "lane": "middle"
    },
    {
        "name": "Zeri",
        "alias": "zeri",
        "gender": "female",
        "resource": "Mana",
        "range_type": ["ranged"],
        "release": 2022,
        "region": "zaun",
        "lane": "bottom"
    },
    {
        "name": "Ziggs",
        "alias": "ziggs",
        "gender": "male",
        "resource": "Mana",
        "range_type": ["ranged"],
        "release": 2012,
        "region": "zaun",
        "lane": "bottom"
    },
    {
        "name": "Zilean",
        "alias": "zilean",
        "gender": "male",
        "resource": "Mana",
        "range_type": ["ranged"],
        "release": 2009,
        "region": "runeterra",
        "lane": "support"
    },
    {
        "name": "Zoe",
        "alias": "zoe",
        "gender": "female",
        "resource": "Mana",
        "range_type": ["ranged"],
        "release": 2017,
        "region": "targon",
        "lane": "middle"
    },
    {
        "name": "Zyra",
        "alias": "zyra",
        "gender": "female",
        "resource": "Mana",
        "range_type": ["ranged"],
        "release": 2012,
        "region": "ixtal",
        "lane": "support"
    }
]
